gj_unitrad/__init__.py
gj_unitrad/analyzer.py
gj_unitrad/compute_index.py
gj_unitrad/unitrade.py
gj_unitrad-0.1.43.dist-info/METADATA
gj_unitrad-0.1.43.dist-info/WHEEL
gj_unitrad-0.1.43.dist-info/top_level.txt
gj_unitrad-0.1.43.dist-info/RECORD
