Metadata-Version: 2.1
Name: gj-unitrad
Version: 0.1.43
Summary: unitrad打包
Author: yanli
Author-email: 1498046515@qq.com
Requires-Python: >3.9
Requires-Dist: pyyaml==6.0.2
Requires-Dist: aiohttp==3.11.10
Requires-Dist: pandas==2.0.0
Requires-Dist: matplotlib==3.9.3
Requires-Dist: Pillow==10.4.0
